msr605_tool-2.4.5.dist-info/licenses/LICENSE
script/MSR605Test.py
script/UI.py
script/__init__.py
script/about.py
script/advanced_functions.py
script/app_menu.py
script/cardReader.py
script/cardReaderExceptions.py
script/card_formats.py
script/card_templates.py
script/card_validation.py
script/connection_setting.py
script/decrypt.py
script/error_handling.py
script/general_setting.py
script/help.py
script/isoStandardDictionary.py
script/language_manager.py
script/log_viewer.py
script/logger.py
script/logging_config.py
script/parser.py
script/performance.py
script/settings_manager.py
script/sponsor.py
script/translations.py
script/updates.py
script/version.py
script/visualization.py
msr605_tool-2.4.5.dist-info/METADATA
msr605_tool-2.4.5.dist-info/WHEEL
msr605_tool-2.4.5.dist-info/entry_points.txt
msr605_tool-2.4.5.dist-info/top_level.txt
msr605_tool-2.4.5.dist-info/RECORD
