Metadata-Version: 2.4
Name: msr605-tool
Version: 2.4.5
Summary: Cross-platform tool for reading, writing, and analyzing magnetic stripe cards using the MSR605 reader/writer
Author-email: Nsfr750 <nsfr750@yandex.com>
Maintainer-email: Nsfr750 <nsfr750@yandex.com>
License: GPL-3.0-or-later
Project-URL: Homepage, https://github.com/Nsfr750/MSR605
Project-URL: Documentation, https://github.com/Nsfr750/MSR605#readme
Project-URL: Issues, https://github.com/Nsfr750/MSR605/issues
Project-URL: Source, https://github.com/Nsfr750/MSR605
Project-URL: Donate, https://paypal.me/3dmega
Classifier: Development Status :: 4 - Beta
Classifier: Intended Audience :: End Users/Desktop
Classifier: Operating System :: OS Independent
Classifier: Programming Language :: Python :: 3.13
Classifier: Topic :: Security
Classifier: Topic :: Utilities
Requires-Python: <3.14,>=3.8
License-File: LICENSE
Requires-Dist: pyserial<4.0,>=3.5
Requires-Dist: cryptography<46.0.0,>=45.0.0
Requires-Dist: wand<0.7.0,>=0.6.13
Requires-Dist: qrcode<8.0.0,>=7.4.0
Requires-Dist: requests<3.0.0,>=2.32.4
Requires-Dist: psutil<6.0.0,>=5.9.0
Requires-Dist: python-dotenv<2.0.0,>=1.0.0
Requires-Dist: PyQt6<6.8.0,>=6.7.0
Requires-Dist: PyQt6-WebEngine<6.8.0,>=6.7.0
Provides-Extra: dev
Requires-Dist: pytest>=8.0.0; extra == "dev"
Requires-Dist: pytest-cov>=4.0.0; extra == "dev"
Requires-Dist: black>=24.0.0; extra == "dev"
Requires-Dist: isort>=5.12.0; extra == "dev"
Requires-Dist: mypy>=1.8.0; extra == "dev"
Requires-Dist: flake8>=7.0.0; extra == "dev"
Requires-Dist: sphinx>=7.0.0; extra == "dev"
Requires-Dist: sphinx-rtd-theme>=1.3.0; extra == "dev"
Dynamic: license-file
